README.md
setup.py
im2txt/__init__.py
im2txt.egg-info/PKG-INFO
im2txt.egg-info/SOURCES.txt
im2txt.egg-info/dependency_links.txt
im2txt.egg-info/top_level.txt