Metadata-Version: 2.1
Name: im2txt
Version: 0.0.3
Summary: Encode images in form of text and decode again!!
Home-page: https://github.com/rrayes3110
Author: Rafael Rayes
Author-email: rafa@rayes.com.br
License: UNKNOWN
Platform: UNKNOWN
Classifier: Programming Language :: Python :: 3
Classifier: License :: OSI Approved :: MIT License
Classifier: Operating System :: OS Independent
